LICENSE
MANIFEST.in
README.md
requirements.txt
setup.py
pyailib/__init__.py
pyailib/version.py
pyailib.egg-info/PKG-INFO
pyailib.egg-info/SOURCES.txt
pyailib.egg-info/dependency_links.txt
pyailib.egg-info/requires.txt
pyailib.egg-info/top_level.txt
pyailib/base/__init__.py
pyailib/base/arrayops.py
pyailib/base/baseops.py
pyailib/base/mathops.py
pyailib/base/randomfunc.py
pyailib/compression/__init__.py
pyailib/compression/huffman_coding.py
pyailib/dsp/__init__.py
pyailib/dsp/convolution.py
pyailib/dsp/correlation.py
pyailib/dsp/ffts.py
pyailib/dsp/function_base.py
pyailib/dsp/interpolation1d.py
pyailib/dsp/interpolation2d.py
pyailib/dsp/normalsignals.py
pyailib/evaluation/__init__.py
pyailib/evaluation/contrast.py
pyailib/evaluation/detection_voc.py
pyailib/evaluation/entropy.py
pyailib/evaluation/error.py
pyailib/evaluation/norm.py
pyailib/evaluation/snr.py
pyailib/misc/__init__.py
pyailib/misc/bounding_box.py
pyailib/misc/draw_shapes.py
pyailib/misc/mapping_operation.py
pyailib/misc/sampling.py
pyailib/misc/transform.py
pyailib/summary/__init__.py
pyailib/summary/loss_log.py
pyailib/utils/__init__.py
pyailib/utils/colormaps.py
pyailib/utils/colors.py
pyailib/utils/const.py
pyailib/utils/convert.py
pyailib/utils/file.py
pyailib/utils/image.py
pyailib/utils/ios.py
pyailib/utils/plot_show.py
pyailib/utils/typevalue.py