Metadata-Version: 2.1
Name: pyailib
Version: 1.1.0
Summary: Python Library.
Home-page: https://iridescent.ink/pyailib/
Author: Zhi Liu
Author-email: zhiliu.mind@gmail.com
License: MIT
Download-URL: https://github.com/antsfamily/pyailib/
Keywords: Python,Library,Digital signal processing,Tool
Platform: UNKNOWN
License-File: LICENSE
